radstats/__init__.py
radstats/bayes.c
radstats/bayes.o
radstats/bayes.py
radstats/core.py
radstats/.vscode/settings.json
radstats-0.0.9.dist-info/WHEEL
radstats-0.0.9.dist-info/METADATA
radstats-0.0.9.dist-info/RECORD
