Metadata-Version: 2.1
Name: radstats
Version: 0.0.9
Summary: radiation effects system modeling tool
Author-email: Stephen Lawrence <rdt249@mocs.utc.edu>
Requires-Python: >=3.9
Classifier: Programming Language :: Python :: 3
Classifier: License :: OSI Approved :: MIT License
Classifier: Operating System :: OS Independent
Requires-Dist: lxml
Requires-Dist: schemdraw
Requires-Dist: numpy
Requires-Dist: pandas
Requires-Dist: scipy
Requires-Dist: Pillow
